Workbook

Sheet Premissas
A1: ELETRIC SOLUTIONS — PREMISSAS (R$ mil)
D2: Ano | E2: FCF projeto
A3: Investimento total | B3: 1000 | D3: 1 | E3: -200
A4: Caixa próprio aportado | B4: 300 | D4: 2 | E4: 150
A5: Gap a financiar | B5: 700 | D5: 3 | E5: 400
A6: g (crescimento perpétuo) | B6: 0.05 | D6: 4 | E6: 550
A7: Taxa de desconto Ku [INPUT] | B7: 0.2 | D7: 5 | E7: 600
A8: Selic | B8: 0.105
A9: Inflação base | B9: 0.045
A10: Taxa empréstimo a.a. | B10: 0.12
A11: Taxa empréstimo mensal | B11: =B10/12
A12: Cupom debênture a.a. | B12: 0.1
A13: Anjo: % equity | B13: 0.2
A14: Anjo: retorno alvo a.a. | B14: 0.25
A15: Taxa desconto mensal | B15: =(1+B7)^(1/12)-1

Sheet Q1_NPV
A1: Q1 — O PROJETO CRIA VALOR?
A3: Ano | B3: FCF | C3: Fator desconto | D3: VP | F3: TIR fluxos explícitos (sem TV) | G3: =IRR(G5:G10)
A4: 1 | B4: =Premissas!E3 | C4: =1/(1+Premissas!$B$7)^A4 | D4: =B4*C4
A5: 2 | B5: =Premissas!E4 | C5: =1/(1+Premissas!$B$7)^A5 | D5: =B5*C5 | F5: (série p/ TIR): | G5: =D12
A6: 3 | B6: =Premissas!E5 | C6: =1/(1+Premissas!$B$7)^A6 | D6: =B6*C6 | G6: =Premissas!E3
A7: 4 | B7: =Premissas!E6 | C7: =1/(1+Premissas!$B$7)^A7 | D7: =B7*C7 | G7: =Premissas!E4
A8: 5 | B8: =Premissas!E7 | C8: =1/(1+Premissas!$B$7)^A8 | D8: =B8*C8 | G8: =Premissas!E5
C9: Soma VP fluxos (anos 1-5) | D9: =SUM(D4:D8) | G9: =Premissas!E6
C10: Valor terminal em t=5 (Gordon) | D10: =Premissas!E7*(1+Premissas!B6)/(Premissas!B7-Premissas!B6) | G10: =Premissas!E7
C11: VP do valor terminal | D11: =D10/(1+Premissas!B7)^5
C12: Investimento (t=0) | D12: =-Premissas!B3
C13: NPV COM perpetuidade | D13: =D12+D9+D11
C14: NPV SEM perpetuidade | D14: =D12+D9
A17: SENSIBILIDADE DA TAXA
A18: Taxa | B18: NPV c/ TV | C18: NPV s/ TV | D18: % no terminal
A19: 0.15 | B19: =-Premissas!$B$3+(Premissas!$E$3/(1+$A19)^1+Premissas!$E$4/(1+$A19)^2+Premissas!$E$5/(1+$A19)^3+Premissas!$E$6/(1+$A19)^4+Premissas!$E$7/(1+$A19)^5)+((Premissas!$E$7*(1+Premissas!$B$6)/($A19-Premissas!$B$6))/(1+$A19)^5) | C19: =-Premissas!$B$3+(Premissas!$E$3/(1+$A19)^1+Premissas!$E$4/(1+$A19)^2+Premissas!$E$5/(1+$A19)^3+Premissas!$E$6/(1+$A19)^4+Premissas!$E$7/(1+$A19)^5) | D19: =((Premissas!$E$7*(1+Premissas!$B$6)/($A19-Premissas!$B$6))/(1+$A19)^5)/((Premissas!$E$3/(1+$A19)^1+Premissas!$E$4/(1+$A19)^2+Premissas!$E$5/(1+$A19)^3+Premissas!$E$6/(1+$A19)^4+Premissas!$E$7/(1+$A19)^5)+((Premissas!$E$7*(1+Premissas!$B$6)/($A19-Premissas!$B$6))/(1+$A19)^5))
A20: 0.18 | B20: =-Premissas!$B$3+(Premissas!$E$3/(1+$A20)^1+Premissas!$E$4/(1+$A20)^2+Premissas!$E$5/(1+$A20)^3+Premissas!$E$6/(1+$A20)^4+Premissas!$E$7/(1+$A20)^5)+((Premissas!$E$7*(1+Premissas!$B$6)/($A20-Premissas!$B$6))/(1+$A20)^5) | C20: =-Premissas!$B$3+(Premissas!$E$3/(1+$A20)^1+Premissas!$E$4/(1+$A20)^2+Premissas!$E$5/(1+$A20)^3+Premissas!$E$6/(1+$A20)^4+Premissas!$E$7/(1+$A20)^5) | D20: =((Premissas!$E$7*(1+Premissas!$B$6)/($A20-Premissas!$B$6))/(1+$A20)^5)/((Premissas!$E$3/(1+$A20)^1+Premissas!$E$4/(1+$A20)^2+Premissas!$E$5/(1+$A20)^3+Premissas!$E$6/(1+$A20)^4+Premissas!$E$7/(1+$A20)^5)+((Premissas!$E$7*(1+Premissas!$B$6)/($A20-Premissas!$B$6))/(1+$A20)^5))
A21: 0.2 | B21: =-Premissas!$B$3+(Premissas!$E$3/(1+$A21)^1+Premissas!$E$4/(1+$A21)^2+Premissas!$E$5/(1+$A21)^3+Premissas!$E$6/(1+$A21)^4+Premissas!$E$7/(1+$A21)^5)+((Premissas!$E$7*(1+Premissas!$B$6)/($A21-Premissas!$B$6))/(1+$A21)^5) | C21: =-Premissas!$B$3+(Premissas!$E$3/(1+$A21)^1+Premissas!$E$4/(1+$A21)^2+Premissas!$E$5/(1+$A21)^3+Premissas!$E$6/(1+$A21)^4+Premissas!$E$7/(1+$A21)^5) | D21: =((Premissas!$E$7*(1+Premissas!$B$6)/($A21-Premissas!$B$6))/(1+$A21)^5)/((Premissas!$E$3/(1+$A21)^1+Premissas!$E$4/(1+$A21)^2+Premissas!$E$5/(1+$A21)^3+Premissas!$E$6/(1+$A21)^4+Premissas!$E$7/(1+$A21)^5)+((Premissas!$E$7*(1+Premissas!$B$6)/($A21-Premissas!$B$6))/(1+$A21)^5))
A22: 0.21 | B22: =-Premissas!$B$3+(Premissas!$E$3/(1+$A22)^1+Premissas!$E$4/(1+$A22)^2+Premissas!$E$5/(1+$A22)^3+Premissas!$E$6/(1+$A22)^4+Premissas!$E$7/(1+$A22)^5)+((Premissas!$E$7*(1+Premissas!$B$6)/($A22-Premissas!$B$6))/(1+$A22)^5) | C22: =-Premissas!$B$3+(Premissas!$E$3/(1+$A22)^1+Premissas!$E$4/(1+$A22)^2+Premissas!$E$5/(1+$A22)^3+Premissas!$E$6/(1+$A22)^4+Premissas!$E$7/(1+$A22)^5) | D22: =((Premissas!$E$7*(1+Premissas!$B$6)/($A22-Premissas!$B$6))/(1+$A22)^5)/((Premissas!$E$3/(1+$A22)^1+Premissas!$E$4/(1+$A22)^2+Premissas!$E$5/(1+$A22)^3+Premissas!$E$6/(1+$A22)^4+Premissas!$E$7/(1+$A22)^5)+((Premissas!$E$7*(1+Premissas!$B$6)/($A22-Premissas!$B$6))/(1+$A22)^5))
A23: 0.25 | B23: =-Premissas!$B$3+(Premissas!$E$3/(1+$A23)^1+Premissas!$E$4/(1+$A23)^2+Premissas!$E$5/(1+$A23)^3+Premissas!$E$6/(1+$A23)^4+Premissas!$E$7/(1+$A23)^5)+((Premissas!$E$7*(1+Premissas!$B$6)/($A23-Premissas!$B$6))/(1+$A23)^5) | C23: =-Premissas!$B$3+(Premissas!$E$3/(1+$A23)^1+Premissas!$E$4/(1+$A23)^2+Premissas!$E$5/(1+$A23)^3+Premissas!$E$6/(1+$A23)^4+Premissas!$E$7/(1+$A23)^5) | D23: =((Premissas!$E$7*(1+Premissas!$B$6)/($A23-Premissas!$B$6))/(1+$A23)^5)/((Premissas!$E$3/(1+$A23)^1+Premissas!$E$4/(1+$A23)^2+Premissas!$E$5/(1+$A23)^3+Premissas!$E$6/(1+$A23)^4+Premissas!$E$7/(1+$A23)^5)+((Premissas!$E$7*(1+Premissas!$B$6)/($A23-Premissas!$B$6))/(1+$A23)^5))
A26: CENÁRIOS (NPV @ Ku, investimento fixo)
A27: Cenário | B27: Fator | C27: NPV c/ TV | D27: NPV s/ TV
A28: Cauda (contração) | B28: 0.5 | C28: =-Premissas!$B$3+($B28*(Premissas!$E$3/(1+Premissas!$B$7)^1+Premissas!$E$4/(1+Premissas!$B$7)^2+Premissas!$E$5/(1+Premissas!$B$7)^3+Premissas!$E$6/(1+Premissas!$B$7)^4+Premissas!$E$7/(1+Premissas!$B$7)^5))+(($B28*Premissas!$E$7*(1+Premissas!$B$6)/(Premissas!$B$7-Premissas!$B$6))/(1+Premissas!$B$7)^5) | D28: =-Premissas!$B$3+($B28*(Premissas!$E$3/(1+Premissas!$B$7)^1+Premissas!$E$4/(1+Premissas!$B$7)^2+Premissas!$E$5/(1+Premissas!$B$7)^3+Premissas!$E$6/(1+Premissas!$B$7)^4+Premissas!$E$7/(1+Premissas!$B$7)^5))
A29: Base | B29: 1 | C29: =-Premissas!$B$3+($B29*(Premissas!$E$3/(1+Premissas!$B$7)^1+Premissas!$E$4/(1+Premissas!$B$7)^2+Premissas!$E$5/(1+Premissas!$B$7)^3+Premissas!$E$6/(1+Premissas!$B$7)^4+Premissas!$E$7/(1+Premissas!$B$7)^5))+(($B29*Premissas!$E$7*(1+Premissas!$B$6)/(Premissas!$B$7-Premissas!$B$6))/(1+Premissas!$B$7)^5) | D29: =-Premissas!$B$3+($B29*(Premissas!$E$3/(1+Premissas!$B$7)^1+Premissas!$E$4/(1+Premissas!$B$7)^2+Premissas!$E$5/(1+Premissas!$B$7)^3+Premissas!$E$6/(1+Premissas!$B$7)^4+Premissas!$E$7/(1+Premissas!$B$7)^5))
A30: Expansão | B30: 1.5 | C30: =-Premissas!$B$3+($B30*(Premissas!$E$3/(1+Premissas!$B$7)^1+Premissas!$E$4/(1+Premissas!$B$7)^2+Premissas!$E$5/(1+Premissas!$B$7)^3+Premissas!$E$6/(1+Premissas!$B$7)^4+Premissas!$E$7/(1+Premissas!$B$7)^5))+(($B30*Premissas!$E$7*(1+Premissas!$B$6)/(Premissas!$B$7-Premissas!$B$6))/(1+Premissas!$B$7)^5) | D30: =-Premissas!$B$3+($B30*(Premissas!$E$3/(1+Premissas!$B$7)^1+Premissas!$E$4/(1+Premissas!$B$7)^2+Premissas!$E$5/(1+Premissas!$B$7)^3+Premissas!$E$6/(1+Premissas!$B$7)^4+Premissas!$E$7/(1+Premissas!$B$7)^5))

Sheet Amort_Price
A1: TABELA PRICE (700k, 1%/mês, 60 meses)
A3: Mês | B3: Saldo inicial | C3: Juros | D3: Amortização | E3: Parcela | F3: Saldo final | H3: Parcela fixa | I3: =$E$4
A4: 1 | B4: =Premissas!$B$5 | C4: =B4*Premissas!$B$11 | D4: =E4-C4 | E4: =PMT(Premissas!$B$11,60,-Premissas!$B$5) | F4: =B4-D4 | H4: Ano 1 (meses 1-12) | I4: =SUM(E4:E15)
A5: 2 | B5: =F4 | C5: =B5*Premissas!$B$11 | D5: =E5-C5 | E5: =$E$4 | F5: =B5-D5 | H5: Total pago | I5: =SUM(E4:E63)
A6: 3 | B6: =F5 | C6: =B6*Premissas!$B$11 | D6: =E6-C6 | E6: =$E$4 | F6: =B6-D6 | H6: Juros totais | I6: =I5-Premissas!B5
A7: 4 | B7: =F6 | C7: =B7*Premissas!$B$11 | D7: =E7-C7 | E7: =$E$4 | F7: =B7-D7 | H7: VP do custo @Ku | I7: =SUMPRODUCT(E4:E63,1/(1+Premissas!$B$15)^A4:A63)
A8: 5 | B8: =F7 | C8: =B8*Premissas!$B$11 | D8: =E8-C8 | E8: =$E$4 | F8: =B8-D8
A9: 6 | B9: =F8 | C9: =B9*Premissas!$B$11 | D9: =E9-C9 | E9: =$E$4 | F9: =B9-D9
A10: 7 | B10: =F9 | C10: =B10*Premissas!$B$11 | D10: =E10-C10 | E10: =$E$4 | F10: =B10-D10
A11: 8 | B11: =F10 | C11: =B11*Premissas!$B$11 | D11: =E11-C11 | E11: =$E$4 | F11: =B11-D11
A12: 9 | B12: =F11 | C12: =B12*Premissas!$B$11 | D12: =E12-C12 | E12: =$E$4 | F12: =B12-D12
A13: 10 | B13: =F12 | C13: =B13*Premissas!$B$11 | D13: =E13-C13 | E13: =$E$4 | F13: =B13-D13
A14: 11 | B14: =F13 | C14: =B14*Premissas!$B$11 | D14: =E14-C14 | E14: =$E$4 | F14: =B14-D14
A15: 12 | B15: =F14 | C15: =B15*Premissas!$B$11 | D15: =E15-C15 | E15: =$E$4 | F15: =B15-D15
A16: 13 | B16: =F15 | C16: =B16*Premissas!$B$11 | D16: =E16-C16 | E16: =$E$4 | F16: =B16-D16
A17: 14 | B17: =F16 | C17: =B17*Premissas!$B$11 | D17: =E17-C17 | E17: =$E$4 | F17: =B17-D17
A18: 15 | B18: =F17 | C18: =B18*Premissas!$B$11 | D18: =E18-C18 | E18: =$E$4 | F18: =B18-D18
A19: 16 | B19: =F18 | C19: =B19*Premissas!$B$11 | D19: =E19-C19 | E19: =$E$4 | F19: =B19-D19
... A63: 60 | B63: =F62 | C63: =B63*Premissas!$B$11 | D63: =E63-C63 | E63: =$E$4 | F63: =B63-D63

Sheet Amort_SAC
A1: SAC (700k, 1%/mês, 60 meses)
A3: Mês | B3: Saldo inicial | C3: Juros | D3: Amortização | E3: Parcela | F3: Saldo final | H3: 1ª parcela | I3: =E4
A4: 1 | B4: =Premissas!$B$5 | C4: =B4*Premissas!$B$11 | D4: =Premissas!$B$5/60 | E4: =C4+D4 | F4: =B4-D4 | H4: última parcela | I4: =E63
A5: 2 | B5: =F4 | C5: =B5*Premissas!$B$11 | D5: =Premissas!$B$5/60 | E5: =C5+D5 | F5: =B5-D5 | H5: Ano 1 (meses 1-12) | I5: =SUM(E4:E15)
A6: 3 | B6: =F5 | C6: =B6*Premissas!$B$11 | D6: =Premissas!$B$5/60 | E6: =C6+D6 | F6: =B6-D6 | H6: Total pago | I6: =SUM(E4:E63)
A7: 4 | B7: =F6 | C7: =B7*Premissas!$B$11 | D7: =Premissas!$B$5/60 | E7: =C7+D7 | F7: =B7-D7 | H7: Juros totais | I7: =I6-Premissas!B5
A8: 5 | B8: =F7 | C8: =B8*Premissas!$B$11 | D8: =Premissas!$B$5/60 | E8: =C8+D8 | F8: =B8-D8 | H8: VP do custo @Ku | I8: =SUMPRODUCT(E4:E63,1/(1+Premissas!$B$15)^A4:A63)
A9: 6 | B9: =F8 | C9: =B9*Premissas!$B$11 | D9: =Premissas!$B$5/60 | E9: =C9+D9 | F9: =B9-D9
A10: 7 | B10: =F9 | C10: =B10*Premissas!$B$11 | D10: =Premissas!$B$5/60 | E10: =C10+D10 | F10: =B10-D10
A11: 8 | B11: =F10 | C11: =B11*Premissas!$B$11 | D11: =Premissas!$B$5/60 | E11: =C11+D11 | F11: =B11-D11
A12: 9 | B12: =F11 | C12: =B12*Premissas!$B$11 | D12: =Premissas!$B$5/60 | E12: =C12+D12 | F12: =B12-D12
A13: 10 | B13: =F12 | C13: =B13*Premissas!$B$11 | D13: =Premissas!$B$5/60 | E13: =C13+D13 | F13: =B13-D13
A14: 11 | B14: =F13 | C14: =B14*Premissas!$B$11 | D14: =Premissas!$B$5/60 | E14: =C14+D14 | F14: =B14-D14
A15: 12 | B15: =F14 | C15: =B15*Premissas!$B$11 | D15: =Premissas!$B$5/60 | E15: =C15+D15 | F15: =B15-D15
A16: 13 | B16: =F15 | C16: =B16*Premissas!$B$11 | D16: =Premissas!$B$5/60 | E16: =C16+D16 | F16: =B16-D16
A17: 14 | B17: =F16 | C17: =B17*Premissas!$B$11 | D17: =Premissas!$B$5/60 | E17: =C17+D17 | F17: =B17-D17
A18: 15 | B18: =F17 | C18: =B18*Premissas!$B$11 | D18: =Premissas!$B$5/60 | E18: =C18+D18 | F18: =B18-D18
A19: 16 | B19: =F18 | C19: =B19*Premissas!$B$11 | D19: =Premissas!$B$5/60 | E19: =C19+D19 | F19: =B19-D19
A20: 17 | B20: =F19 | C20: =B20*Premissas!$B$11 | D20: =Premissas!$B$5/60 | E20: =C20+D20 | F20: =B20-D20
... A63: 60 | B63: =F62 | C63: =B63*Premissas!$B$11 | D63: =Premissas!$B$5/60 | E63: =C63+D63 | F63: =B63-D63

Sheet Q2_Custos
A1: Q2 — QUANTO CUSTA CADA OPÇÃO (R$ mil)
A3: Opção | B3: Total nominal pago | C3: Custo (juros/prêmio) | D3: Caixa ano 1 | E3: VP do custo @Ku | F3: VP por R$ captado
A4: Debênture (bullet) | B4: =70*5+Premissas!B5 | C4: 350 | D4: 70 | E4: =70/(1+Premissas!B7)^1+70/(1+Premissas!B7)^2+70/(1+Premissas!B7)^3+70/(1+Premissas!B7)^4+(70+Premissas!B5)/(1+Premissas!B7)^5 | F4: =E4/Premissas!B5
A5: Price | B5: =Amort_Price!I5 | C5: =Amort_Price!I6 | D5: =Amort_Price!I4 | E5: =Amort_Price!I7 | F5: =E5/Premissas!B5
A6: SAC | B6: =Amort_SAC!I6 | C6: =Amort_SAC!I7 | D6: =Amort_SAC!I5 | E6: =Amort_SAC!I8 | F6: =E6/Premissas!B5
A7: Anjo (equity 20%) | B7: 20% equity | C7: =Premissas!B5*(1+Premissas!B14)^5-Premissas!B5 | D7: 0 | E7: =Premissas!B5*(1+Premissas!B14)^5/(1+Premissas!B7)^5 | F7: =E7/Premissas!B5
A9: Ranking VP: Debênture < Price < SAC < Anjo. Debênture paga MAIS juro nominal mas é a mais barata em VP (inversão).
A10: Anjo: VP é o piso (cenário-base). Na expansão a empresa vale mais e o custo do anjo dispara.
A12: PERFIL DE CAIXA ANUAL (R$ mil)
A13: Ano | B13: Price | C13: SAC | D13: Debênture | E13: Anjo
A14: 1 | B14: =SUM(Amort_Price!E4:E15) | C14: =SUM(Amort_SAC!E4:E15) | D14: 70 | E14: 0
A15: 2 | B15: =SUM(Amort_Price!E16:E27) | C15: =SUM(Amort_SAC!E16:E27) | D15: 70 | E15: 0
A16: 3 | B16: =SUM(Amort_Price!E28:E39) | C16: =SUM(Amort_SAC!E28:E39) | D16: 70 | E16: 0
A17: 4 | B17: =SUM(Amort_Price!E40:E51) | C17: =SUM(Amort_SAC!E40:E51) | D17: 70 | E17: 0
A18: 5 | B18: =SUM(Amort_Price!E52:E63) | C18: =SUM(Amort_SAC!E52:E63) | D18: =70+Premissas!B5 | E18: 0

Sheet Q3_Q4_Q5
A1: Q3-Q5 — RECOMENDAÇÃO, CENÁRIOS, PREMISSA CRÍTICA
A3: EIXO DA DECISÃO (debate convergido): Price vs Anjo. Debênture e SAC descartados.
A4: • Debênture: mais barata em VP, mas reintroduz risco de cauda (bullet 770k em 2031) — o feature que a Q3 pede pra evitar.
A5: • SAC: dominado pela Price (mais pesado no ano frágil, VP maior).
A7: Q3 — RECOMENDAÇÃO (duas opções defensáveis):
A8: OPÇÃO A — PRICE: se a empresa tem QUALQUER folga de caixa operacional.
A9: Por quê: dívida mais barata que preserva 100% do equity, elimina o bullet, parcela fixa de ~187k/ano.
A10: Risco que aceito: obrigação rígida; se um cliente sai E o projeto atrasa, 187k/ano aperta o caixa.
A12: OPÇÃO B — ANJO: se a estrutura de custos é pesada (15 engenheiros fixos; sócios aportaram 800k e só restam 300k).
A13: Por quê: zero obrigação; única estrutura que sobrevive ao estado em que nem a parcela da Price se paga.
A14: Risco que aceito: o mais caro no sucesso (cede 20% do upside, que é 70-79% do valor) — 'arrependimento de sucesso'.
A16: O QUE OS SEPARA: a largura da faixa 'nem a Price se serve'. É função da estrutura de custos, que o case não dá em número.
... A29: NOTA: a dívida se paga com CAIXA LIVRE, não receita. Com 2 clientes + custo fixo, perder 1 pode zerar o caixa livre — é o nó do debate.
