Workbook

Sheet Resumo
A1: ELETRIC SOLUTIONS — PRICE vs ANJO COM CALLBACK (R$ mil)
A3: Métrica | B3: PRICE | C3: ANJO COM CALLBACK
A4: Captação dos R$ 700k | B4: Dívida, 12% a.a. (1%/mês), 60 meses | C4: Equity por 20% + opção de recompra
A5: Taxa de desconto do projeto (Ku) | B5: =Premissas!B7 -> 0.2 | C5: =Premissas!B7 -> 0.2
A6: VPL DO PROJETO (igual, MM) | B6: =Premissas!G4 -> 1363.233 | C6: =Premissas!G4 -> 1363.233
A7: Desembolso anos 1-5 | B7: =TEXT(Price!I4,"#,##0") & " /ano (fixo)" -> 186,853 /ano (fixo) | C7: ZERO
A8: VP do custo do financiamento | B8: =Price!I7 -> 608.3445 | C8: =Anjo!C4 -> 858.50311
A9: Extração do financiador (VP) | B9: =Price!I8 -> -91.655502 | C9: =Anjo!D4 -> 158.50311
A10: VPL PARA OS FUNDADORES | B10: =Price!I9 -> 1454.8885 | C10: =Anjo!E4 -> 1204.7299
A11: Equity final dos fundadores | B11: 100% | C11: 100% se exercer / 80% se não
A12: Proteção de downside | B12: Não (dívida rígida) | C12: Sim (zero obrigação)
A13: Risco que se aceita | B13: Obrigação rígida sufoca no choque | C13: Mais caro; caixa p/ recompra; anjo aceitar teto
A16: Proposta:
A17: Recomendamos Price se o caixa livre aguenta a parcela de 187k/ano mesmo num cenário de perda de cliente, é a mais barata, mantém 100% do equity, devolve +1.455k ao fundador. Se o caixa é frágil demais pra essa obrigação rígida no período de queima, vou de anjo com callback, zera a obrigação e protege o downside, e a recompra no ano 5 me devolve o equity em vez de cedê-lo pra sempre. Paga um prêmio por isso (VPL fundador cai pra ~1.205k), mas é o preço do seguro.

Sheet Premissas
A1: PREMISSAS (R$ mil)
D2: Ano | E2: FCF | G2: VALUATION DO PROJETO
A3: Investimento total | B3: 1000 | D3: 1 | E3: -200 | F3: PV das entradas | G3: =SUMPRODUCT(E3:E7,1/(1+B7)^D3:D7)+(E7*(1+B6)/(B7-B6))/(1+B7)^5 -> 2363.233
A4: Caixa próprio | B4: 300 | D4: 2 | E4: 150 | F4: VPL do projeto | G4: =-B3+G3 -> 1363.233
A5: Gap a financiar | B5: 700 | D5: 3 | E5: 400 | F5: Valor terminal (t=5) | G5: =E7*(1+B6)/(B7-B6) -> 4200
A6: g (crescimento perpétuo) | B6: 0.05 | D6: 4 | E6: 550
A7: Taxa desconto Ku [INPUT] | B7: 0.2 | D7: 5 | E7: 600
A8: Selic | B8: 0.105
A9: Taxa empréstimo a.a. | B9: 0.12
A10: Taxa empréstimo mensal | B10: =B9/12 -> 0.01
A11: Taxa desconto mensal | B11: =(1+B7)^(1/12)-1 -> 0.01530947
A12: Anjo: strike recompra [INPUT] | B12: 0.25

Sheet Price
A1: PRICE — 700k, 1%/mês, 60 meses
A3: Mês | B3: Saldo ini. | C3: Juros | D3: Amort. | E3: Parcela | F3: Saldo fim | H3: Parcela/mês | I3: =E4 -> 15.571113
A4: 1 | B4: =Premissas!$B$5 -> 700 | C4: =B4*Premissas!$B$10 -> 7 | D4: =E4-C4 -> 8.5711134 | E4: =PMT(Premissas!$B$10,60,-Premissas!$B$5) -> 15.571113 | F4: =B4-D4 -> 691.42889 | H4: Desembolso ano 1 | I4: =SUM(E4:E15) -> 186.85336
A5: 2 | B5: =F4 -> 691.42889 | C5: =B5*Premissas!$B$10 -> 6.9142889 | D5: =E5-C5 -> 8.6568245 | E5: =$E$4 -> 15.571113 | F5: =B5-D5 -> 682.77206 | H5: Total pago | I5: =SUM(E4:E63) -> 934.2668
A6: 3 | B6: =F5 -> 682.77206 | C6: =B6*Premissas!$B$10 -> 6.8277206 | D6: =E6-C6 -> 8.7433928 | E6: =$E$4 -> 15.571113 | F6: =B6-D6 -> 674.02867 | H6: Juros totais | I6: =I5-Premissas!B5 -> 234.2668
A7: 4 | B7: =F6 -> 674.02867 | C7: =B7*Premissas!$B$10 -> 6.7402867 | D7: =E7-C7 -> 8.8308267 | E7: =$E$4 -> 15.571113 | F7: =B7-D7 -> 665.19784 | H7: VP do custo @Ku | I7: =SUMPRODUCT(E4:E63,1/(1+Premissas!$B$11)^A4:A63) -> 608.3445
A8: 5 | B8: =F7 -> 665.19784 | C8: =B8*Premissas!$B$10 -> 6.6519784 | D8: =E8-C8 -> 8.919135 | E8: =$E$4 -> 15.571113 | F8: =B8-D8 -> 656.27871 | H8: Extração do banco (VP-700) | I8: =I7-Premissas!B5 -> -91.655502
A9: 6 | B9: =F8 -> 656.27871 | C9: =B9*Premissas!$B$10 -> 6.5627871 | D9: =E9-C9 -> 9.0083263 | E9: =$E$4 -> 15.571113 | F9: =B9-D9 -> 647.27038 | H9: VPL FUNDADORES | I9: =-Premissas!B4+Premissas!G3-I7 -> 1454.8885
A10: 7 | B10: =F9 -> 647.27038 | C10: =B10*Premissas!$B$10 -> 6.4727038 | D10: =E10-C10 -> 9.0984096 | E10: =$E$4 -> 15.571113 | F10: =B10-D10 -> 638.17197
A11: 8 | B11: =F10 -> 638.17197 | C11: =B11*Premissas!$B$10 -> 6.3817197 | D11: =E11-C11 -> 9.1893937 | E11: =$E$4 -> 15.571113 | F11: =B11-D11 -> 628.98258
A12: 9 | B12: =F11 -> 628.98258 | C12: =B12*Premissas!$B$10 -> 6.2898258 | D12: =E12-C12 -> 9.2812876 | E12: =$E$4 -> 15.571113 | F12: =B12-D12 -> 619.70129
A13: 10 | B13: =F12 -> 619.70129 | C13: =B13*Premissas!$B$10 -> 6.1970129 | D13: =E13-C13 -> 9.3741005 | E13: =$E$4 -> 15.571113 | F13: =B13-D13 -> 610.32719
A14: 11 | B14: =F13 -> 610.32719 | C14: =B14*Premissas!$B$10 -> 6.1032719 | D14: =E14-C14 -> 9.4678415 | E14: =$E$4 -> 15.571113 | F14: =B14-D14 -> 600.85935
A15: 12 | B15: =F14 -> 600.85935 | C15: =B15*Premissas!$B$10 -> 6.0085935 | D15: =E15-C15 -> 9.5625199 | E15: =$E$4 -> 15.571113 | F15: =B15-D15 -> 591.29683
A16: 13 | B16: =F15 -> 591.29683 | C16: =B16*Premissas!$B$10 -> 5.9129683 | D16: =E16-C16 -> 9.6581451 | E16: =$E$4 -> 15.571113 | F16: =B16-D16 -> 581.63868
A17: 14 | B17: =F16 -> 581.63868 | C17: =B17*Premissas!$B$10 -> 5.8163868 | D17: =E17-C17 -> 9.7547265 | E17: =$E$4 -> 15.571113 | F17: =B17-D17 -> 571.88396
A18: 15 | B18: =F17 -> 571.88396 | C18: =B18*Premissas!$B$10 -> 5.7188396 | D18: =E18-C18 -> 9.8522738 | E18: =$E$4 -> 15.571113 | F18: =B18-D18 -> 562.03168
A19: 16 | B19: =F18 -> 562.03168 | C19: =B19*Premissas!$B$10 -> 5.6203168 | D19: =E19-C19 -> 9.9507965 | E19: =$E$4 -> 15.571113 | F19: =B19-D19 -> 552.08089
A20: 17 | B20: =F19 -> 552.08089 | C20: =B20*Premissas!$B$10 -> 5.5208089 | D20: =E20-C20 -> 10.050305 | E20: =$E$4 -> 15.571113 | F20: =B20-D20 -> 542.03058
A21: 18 | B21: =F20 -> 542.03058 | C21: =B21*Premissas!$B$10 -> 5.4203058 | D21: =E21-C21 -> 10.150808 | E21: =$E$4 -> 15.571113 | F21: =B21-D21 -> 531.87977
... A63: 60 | B63: =F62 -> 15.416944 | C63: =B63*Premissas!$B$10 -> 0.15416944 | D63: =E63-C63 -> 15.416944 | E63: =$E$4 -> 15.571113 | F63: =B63-D63 -> 4.2277293e-13

Sheet Anjo
A1: ANJO COM CALLBACK — 700k por 20%, recompra opcional no ano 5
A3: Strike a.a. | B3: Recompra nominal (ano 5) | C3: VP recompra @Ku | D3: Extração (VP-700) | E3: VPL FUNDADORES
A4: 0.25 | B4: =Premissas!$B$5*(1+A4)^5 -> 2136.2305 | C4: =B4/(1+Premissas!$B$7)^5 -> 858.50311 | D4: =C4-Premissas!$B$5 -> 158.50311 | E4: =Premissas!$G$4-D4 -> 1204.7299
A5: 0.28 | B5: =Premissas!$B$5*(1+A5)^5 -> 2405.1817 | C5: =B5/(1+Premissas!$B$7)^5 -> 966.58858 | D5: =C5-Premissas!$B$5 -> 266.58858 | E5: =Premissas!$G$4-D5 -> 1096.6444
A6: 0.3 | B6: =Premissas!$B$5*(1+A6)^5 -> 2599.051 | C6: =B6/(1+Premissas!$B$7)^5 -> 1044.5003 | D6: =C6-Premissas!$B$5 -> 344.50031 | E6: =Premissas!$G$4-D6 -> 1018.7327
A8: POR QUE CALLBACK e não anjo puro (efeito no SUCESSO +50%):
A9: Anjo PURO: 20% acompanha a empresa. Se vale ~16M em 2031, 20% = VP ~1.286k -> extração +586 -> VPL fundadores cai p/ ~777k.
A10: Anjo CALLBACK: recompra TRAVADA no strike -> extração fica em +159 a +345 -> VPL fundadores segura ~1.0-1.2M mesmo no sucesso.
A11: Ou seja: o callback capa a única fraqueza do anjo (ceder upside pra sempre). No fracasso, não exerce: dá os 20% (que valem pouco) e zera obrigação.

Sheet Cenarios
A1: COMPORTAMENTO NOS CENÁRIOS (Q4)
A3: Cenário | B3: PRICE | C3: ANJO COM CALLBACK
A4: Contração (metade) | B4: Servido por negócio existente + caixa do projeto; sobrevive | C4: Zero obrigação; totalmente protegido
A5: Expansão (+50%) | B5: Custo fixo; fundadores ficam com TODO o upside (+1.455k segura) | C5: Exerce recompra travada; retoma 100%; custo capado
A6: Inflação alta (7%) | B6: Custo real da parcela cai (nominal fixa, Fisher) | C6: Recompra também é nominal fixa; também se beneficia
