Workbook

Sheet Premissas
A1: CASO PIPOCA DO ZEZINHO: demonstracoes financeiras
A2: Valores em $. Legenda: | B2: azul = input do caso | C2: preto = formula | D2: verde = link entre abas | E2: amarelo = preencher (enunciado M3)
A4: Dia 1 (fase aposentado)
A5: Vendas do dia | B5: 125
A6: Ingredientes consumidos | B6: 25
A7: Aluguel do carrinho (diario) | B7: 20
A8: Salario | B8: 0
A10: Meses (fase com funcionario) | C10: M1 | D10: M2 | E10: M3
A11: Vendas do mes | C11: 3200 | D11: 3400
A12: % recebido a vista | C12: 1 | D12: 0.5
A13: Compras de ingredientes | C13: 700 | D13: 1340
A14: Ingredientes consumidos (CMV) | C14: 700 | D14: 680
A15: Salario do mes | C15: 750 | D15: 750 | E15: 750
A16: Aluguel do mes | C16: 600 | D16: 600 | E16: 600
A18: Prazos de pagamento e recebimento
A19: Salario: pago dia 05 do mes seguinte
A20: Supermercado: pago dia 15 do mes seguinte
A21: Aluguel: pago dia 01 do mes seguinte
A22: Cartao de credito: recebido no mes seguinte
A23: Dividendos: 100% do lucro, pagos dentro do proprio mes
A25: Gabarito do quiz (Tema 4)
A26: Lucro (quiz) | C26: 1150 | D26: 1370 | E26: 1590
A27: Caixa das operacoes (quiz) | C27: 3200 | D27: -350 | E27: 1260

Sheet DRE
A1: DRE (regime de competencia)
B2: Dia 1 | C2: M1 | D2: M2
A3: Receita de vendas | B3: =Premissas!B5 -> 125 | C3: =Premissas!C11 -> 3200 | D3: =Premissas!D11 -> 3400
A4: (-) CMV (ingredientes consumidos) | B4: =-Premissas!B6 -> -25 | C4: =-Premissas!C14 -> -700 | D4: =-Premissas!D14 -> -680
A5: Lucro bruto | B5: =SUM(B3:B4) -> 100 | C5: =SUM(C3:C4) -> 2500 | D5: =SUM(D3:D4) -> 2720
A6: (-) Salario | B6: =-Premissas!B8 -> 0 | C6: =-Premissas!C15 -> -750 | D6: =-Premissas!D15 -> -750
A7: (-) Aluguel | B7: =-Premissas!B7 -> -20 | C7: =-Premissas!C16 -> -600 | D7: =-Premissas!D16 -> -600
A8: Lucro liquido | B8: =B5+B6+B7 -> 80 | C8: =C5+C6+C7 -> 1150 | D8: =D5+D6+D7 -> 1370
A10: Lucro pelo quiz | C10: =Premissas!C26 -> 1150 | D10: =Premissas!D26 -> 1370
A11: Check (calculado - quiz) | C11: =C8-C10 -> 0 | D11: =D8-D10 -> 0
A13: M3: preencher Premissas (amarelo) para a coluna; lucro oficial 1.590.

Sheet DFC
A1: DFC (metodo direto)
B2: M1 | C2: M2 | D2: M3
A3: Recebimentos de clientes | B3: =Premissas!C11*Premissas!C12 -> 3200 | C3: =Premissas!D11*Premissas!D12+Premissas!C11*(1-Premissas!C12) -> 1700
A4: (-) Pagamento a fornecedores | B4: 0 | C4: =-Premissas!C13 -> -700
A5: (-) Pagamento de salarios | B5: 0 | C5: =-Premissas!C15 -> -750
A6: (-) Pagamento de alugueis | B6: 0 | C6: =-Premissas!C16 -> -600
A7: Caixa das operacoes (FCO) | B7: =SUM(B3:B6) -> 3200 | C7: =SUM(C3:C6) -> -350 | D7: 1260
A9: (-) Dividendos pagos (FCF) | B9: =-DRE!C8 -> -1150 | C9: =-DRE!D8 -> -1370 | D9: =-Premissas!E26 -> -1590
A10: Variacao de caixa | B10: =B7+B9 -> 2050 | C10: =C7+C9 -> -1720 | D10: =D7+D9 -> -330
A11: Caixa inicial | B11: 0 | C11: =B12 -> 2050 | D11: =C12 -> 330
A12: Caixa final | B12: =B10+B11 -> 2050 | C12: =C10+C11 -> 330 | D12: =D10+D11 -> 0
A14: Check FCO (calculado - quiz) | B14: =B7-Premissas!C27 -> 0 | C14: =C7-Premissas!D27 -> 0 | D14: =D7-Premissas!E27 -> 0

Sheet BP
A1: Balanco Patrimonial (fim do mes, apos dividendo)
B2: Fim M1 | C2: Fim M2
A3: ATIVO
A4: Caixa | B4: =DFC!B12 -> 2050 | C4: =DFC!C12 -> 330
A5: Contas a receber (cartao) | B5: =Premissas!C11*(1-Premissas!C12) -> 0 | C5: =Premissas!D11*(1-Premissas!D12) -> 1700
A6: Estoque | B6: =Premissas!C13-Premissas!C14 -> 0 | C6: =B6+Premissas!D13-Premissas!D14 -> 660
A7: Total do ativo | B7: =SUM(B4:B6) -> 2050 | C7: =SUM(C4:C6) -> 2690
A9: PASSIVO
A10: Fornecedores | B10: =Premissas!C13 -> 700 | C10: =Premissas!D13 -> 1340
A11: Salarios a pagar | B11: =Premissas!C15 -> 750 | C11: =Premissas!D15 -> 750
A12: Alugueis a pagar | B12: =Premissas!C16 -> 600 | C12: =Premissas!D16 -> 600
A13: Total do passivo | B13: =SUM(B10:B12) -> 2050 | C13: =SUM(C10:C12) -> 2690
A15: PATRIMONIO LIQUIDO
A16: Capital social | B16: 0 | C16: =B16 -> 0
A17: Lucros acumulados | B17: =DRE!C8+DFC!B9 -> 0 | C17: =B17+DRE!D8+DFC!C9 -> 0
A18: Total do PL | B18: =B16+B17 -> 0 | C18: =C16+C17 -> 0
A20: Passivo + PL | B20: =B13+B18 -> 2050 | C20: =C13+C18 -> 2690
A21: Check (Ativo - Passivo - PL) | B21: =B7-B20 -> 0 | C21: =C7-C20 -> 0
A23: Fim de M3 fica pendente do enunciado (contas a receber e estoque finais).
