Workbook

Sheet Premissas
A1: CASO PIPOCA DO ZEZINHO (A e B): demonstracoes financeiras
A2: Valores em $. Legenda: | B2: azul = input do caso | C2: preto = formula | D2: verde = link entre abas
A4: Dia 1 (fase aposentado)
A5: Vendas do dia | B5: 125
A6: Ingredientes consumidos | B6: 25
A7: Aluguel do carrinho (diario) | B7: 20
A8: Salario | B8: 0
A10: Meses (fase com funcionario) | C10: M1 | D10: M2 | E10: M3
A11: Vendas do mes | C11: 3200 | D11: 3400 | E11: 3600
A12: % recebido a vista | C12: 1 | D12: 0.5 | E12: 1
A13: Compras de ingredientes | C13: 700 | D13: 1340 | E13: 0
A14: Ingredientes consumidos (CMV) | C14: 700 | D14: 680 | E14: =C13-C14+D13-D14+E13 -> 660
A15: Salario do mes | C15: 750 | D15: 750 | E15: 750
A16: Aluguel do mes | C16: 600 | D16: 600 | E16: 600
A17: Salario+aluguel do mes pagos dentro do proprio mes? (1=sim) | C17: 0 | D17: 0 | E17: 1
A19: Prazos de pagamento e recebimento
A20: Salario: pago dia 05 do mes seguinte (M3: pago no proprio mes)
A21: Supermercado: pago dia 15 do mes seguinte
A22: Aluguel: pago dia 01 do mes seguinte (M3: pago no proprio mes)
A23: Cartao de credito: recebido no mes seguinte
A24: Dividendos: 100% do lucro, pagos dentro do proprio mes
A26: Gabarito do quiz (Tema 4)
A27: Lucro (quiz) | C27: 1150 | D27: 1370 | E27: 1590
A28: Caixa das operacoes (quiz) | C28: 3200 | D28: -350 | E28: 1260

Sheet DRE
A1: DRE (regime de competencia)
B2: Dia 1 | C2: M1 | D2: M2 | E2: M3 | F2: Trimestre
A3: Receita de vendas | B3: =Premissas!B5 -> 125 | C3: =Premissas!C11 -> 3200 | D3: =Premissas!D11 -> 3400 | E3: =Premissas!E11 -> 3600 | F3: =SUM(C3:E3) -> 10200
A4: (-) CMV (ingredientes consumidos) | B4: =-Premissas!B6 -> -25 | C4: =-Premissas!C14 -> -700 | D4: =-Premissas!D14 -> -680 | E4: =-Premissas!E14 -> -660 | F4: =SUM(C4:E4) -> -2040
A5: Lucro bruto | B5: =SUM(B3:B4) -> 100 | C5: =SUM(C3:C4) -> 2500 | D5: =SUM(D3:D4) -> 2720 | E5: =SUM(E3:E4) -> 2940 | F5: =SUM(C5:E5) -> 8160
A6: (-) Salario | B6: =-Premissas!B8 -> 0 | C6: =-Premissas!C15 -> -750 | D6: =-Premissas!D15 -> -750 | E6: =-Premissas!E15 -> -750 | F6: =SUM(C6:E6) -> -2250
A7: (-) Aluguel | B7: =-Premissas!B7 -> -20 | C7: =-Premissas!C16 -> -600 | D7: =-Premissas!D16 -> -600 | E7: =-Premissas!E16 -> -600 | F7: =SUM(C7:E7) -> -1800
A8: Lucro liquido | B8: =B5+B6+B7 -> 80 | C8: =C5+C6+C7 -> 1150 | D8: =D5+D6+D7 -> 1370 | E8: =E5+E6+E7 -> 1590 | F8: =SUM(C8:E8) -> 4110
A10: Lucro pelo quiz | C10: =Premissas!C27 -> 1150 | D10: =Premissas!D27 -> 1370 | E10: =Premissas!E27 -> 1590
A11: Check (calculado - quiz) | C11: =C8-C10 -> 0 | D11: =D8-D10 -> 0 | E11: =E8-E10 -> 0

Sheet DFC
A1: DFC (metodo direto)
B2: M1 | C2: M2 | D2: M3 | E2: Trimestre
A3: Recebimento de vendas a vista do mes | B3: =Premissas!C11*Premissas!C12 -> 3200 | C3: =Premissas!D11*Premissas!D12 -> 1700 | D3: =Premissas!E11*Premissas!E12 -> 3600 | E3: =SUM(B3:D3) -> 8500
A4: Recebimento do cartao do mes anterior | B4: 0 | C4: =Premissas!C11*(1-Premissas!C12) -> 0 | D4: =Premissas!D11*(1-Premissas!D12) -> 1700 | E4: =SUM(B4:D4) -> 1700
A5: (-) Fornecedor do mes anterior | B5: 0 | C5: =-Premissas!C13 -> -700 | D5: =-Premissas!D13 -> -1340 | E5: =SUM(B5:D5) -> -2040
A6: (-) Salario do mes anterior | B6: 0 | C6: =-Premissas!C15*(1-Premissas!C17) -> -750 | D6: =-Premissas!D15*(1-Premissas!D17) -> -750 | E6: =SUM(B6:D6) -> -1500
A7: (-) Aluguel do mes anterior | B7: 0 | C7: =-Premissas!C16*(1-Premissas!C17) -> -600 | D7: =-Premissas!D16*(1-Premissas!D17) -> -600 | E7: =SUM(B7:D7) -> -1200
A8: (-) Salario e aluguel do proprio mes (se pagos no mes) | B8: =-(Premissas!C15+Premissas!C16)*Premissas!C17 -> 0 | C8: =-(Premissas!D15+Premissas!D16)*Premissas!D17 -> 0 | D8: =-(Premissas!E15+Premissas!E16)*Premissas!E17 -> -1350 | E8: =SUM(B8:D8) -> -1350
A9: Caixa das operacoes (FCO) | B9: =SUM(B3:B8) -> 3200 | C9: =SUM(C3:C8) -> -350 | D9: =SUM(D3:D8) -> 1260 | E9: =SUM(B9:D9) -> 4110
A11: (-) Dividendos pagos (FCF) | B11: =-DRE!C8 -> -1150 | C11: =-DRE!D8 -> -1370 | D11: =-DRE!E8 -> -1590 | E11: =SUM(B11:D11) -> -4110
A12: Variacao de caixa | B12: =B9+B11 -> 2050 | C12: =C9+C11 -> -1720 | D12: =D9+D11 -> -330 | E12: =SUM(B12:D12) -> 0
A13: Caixa inicial | B13: 0 | C13: =B14 -> 2050 | D13: =C14 -> 330 | E13: =B13 -> 0
A14: Caixa final | B14: =B12+B13 -> 2050 | C14: =C12+C13 -> 330 | D14: =D12+D13 -> 0 | E14: =E12+E13 -> 0
A16: Check FCO (calculado - quiz) | B16: =B9-Premissas!C28 -> 0 | C16: =C9-Premissas!D28 -> 0 | D16: =D9-Premissas!E28 -> 0
A18: Q6: total de dividendos nos 3 meses | B18: =-E11 -> 4110
A19: Lucro acumulado do trimestre (DRE) | B19: =DRE!F8 -> 4110
A20: FCO acumulado do trimestre | B20: =E9 -> 4110

Sheet BP
A1: Balanco Patrimonial (fim do mes, apos dividendo)
B2: Fim M1 | C2: Fim M2 | D2: Fim M3
A3: ATIVO
A4: Caixa | B4: =DFC!B14 -> 2050 | C4: =DFC!C14 -> 330 | D4: =DFC!D14 -> 0
A5: Contas a receber (cartao) | B5: =Premissas!C11*(1-Premissas!C12) -> 0 | C5: =Premissas!D11*(1-Premissas!D12) -> 1700 | D5: =Premissas!E11*(1-Premissas!E12) -> 0
A6: Estoque | B6: =Premissas!C13-Premissas!C14 -> 0 | C6: =B6+Premissas!D13-Premissas!D14 -> 660 | D6: =C6+Premissas!E13-Premissas!E14 -> 0
A7: Total do ativo | B7: =SUM(B4:B6) -> 2050 | C7: =SUM(C4:C6) -> 2690 | D7: =SUM(D4:D6) -> 0
A9: PASSIVO
A10: Fornecedores | B10: =Premissas!C13 -> 700 | C10: =Premissas!D13 -> 1340 | D10: =Premissas!E13 -> 0
A11: Salarios a pagar | B11: =Premissas!C15*(1-Premissas!C17) -> 750 | C11: =Premissas!D15*(1-Premissas!D17) -> 750 | D11: =Premissas!E15*(1-Premissas!E17) -> 0
A12: Alugueis a pagar | B12: =Premissas!C16*(1-Premissas!C17) -> 600 | C12: =Premissas!D16*(1-Premissas!D17) -> 600 | D12: =Premissas!E16*(1-Premissas!E17) -> 0
A13: Total do passivo | B13: =SUM(B10:B12) -> 2050 | C13: =SUM(C10:C12) -> 2690 | D13: =SUM(D10:D12) -> 0
A15: PATRIMONIO LIQUIDO
A16: Capital social | B16: 0 | C16: =B16 -> 0 | D16: =C16 -> 0
A17: Lucros acumulados | B17: =DRE!C8+DFC!B11 -> 0 | C17: =B17+DRE!D8+DFC!C11 -> 0 | D17: =C17+DRE!E8+DFC!D11 -> 0
A18: Total do PL | B18: =B16+B17 -> 0 | C18: =C16+C17 -> 0 | D18: =D16+D17 -> 0
A20: Passivo + PL | B20: =B13+B18 -> 2050 | C20: =C13+C18 -> 2690 | D20: =D13+D18 -> 0
A21: Check (Ativo - Passivo - PL) | B21: =B7-B20 -> 0 | C21: =C7-C20 -> 0 | D21: =D7-D20 -> 0
A23: Fim de M3: balanco zerado. Sem caixa, sem recebiveis, sem estoque, sem dividas, PL zero.
